{
    "id": 34,
    "name": "map_34",
    "areas_nao_navegaveis": [
        {
            "id": 0,
            "name": "nf_0",
            "cartesian_points": [
                [
                    2.14,
                    -6.34,
                    0
                ],
                [
                    1.13,
                    -6.18,
                    0
                ],
                [
                    1.29,
                    -5.16,
                    0
                ],
                [
                    2.3,
                    -5.33,
                    0
                ]
            ]
        },
        {
            "id": 1,
            "name": "nf_1",
            "cartesian_points": [
                [
                    -2.16,
                    -5.12,
                    0
                ],
                [
                    -3.79,
                    -5.33,
                    0
                ],
                [
                    -4.0,
                    -3.69,
                    0
                ],
                [
                    -2.36,
                    -3.49,
                    0
                ]
            ]
        },
        {
            "id": 2,
            "name": "nf_2",
            "cartesian_points": [
                [
                    1.36,
                    -4.0,
                    0
                ],
                [
                    0.52,
                    -4.1,
                    0
                ],
                [
                    0.42,
                    -3.26,
                    0
                ],
                [
                    1.26,
                    -3.15,
                    0
                ]
            ]
        },
        {
            "id": 3,
            "name": "nf_3",
            "cartesian_points": [
                [
                    1.8,
                    -7.13,
                    0
                ],
                [
                    0.31,
                    -6.93,
                    0
                ],
                [
                    0.51,
                    -5.45,
                    0
                ],
                [
                    1.99,
                    -5.65,
                    0
                ]
            ]
        },
        {
            "id": 4,
            "name": "nf_4",
            "cartesian_points": [
                [
                    1.21,
                    -5.85,
                    0
                ],
                [
                    0.78,
                    -5.66,
                    0
                ],
                [
                    0.97,
                    -5.23,
                    0
                ],
                [
                    1.4,
                    -5.42,
                    0
                ]
            ]
        },
        {
            "id": 5,
            "name": "nf_5",
            "cartesian_points": [
                [
                    0.48,
                    -6.07,
                    0
                ],
                [
                    -0.02,
                    -5.83,
                    0
                ],
                [
                    0.21,
                    -5.32,
                    0
                ],
                [
                    0.72,
                    -5.56,
                    0
                ]
            ]
        },
        {
            "id": 6,
            "name": "nf_6",
            "cartesian_points": [
                [
                    2.93,
                    -1.59,
                    0
                ],
                [
                    2.66,
                    -0.59,
                    0
                ],
                [
                    3.66,
                    -0.32,
                    0
                ],
                [
                    3.93,
                    -1.32,
                    0
                ]
            ]
        },
        {
            "id": 7,
            "name": "nf_7",
            "cartesian_points": [
                [
                    -4.71,
                    -5.83,
                    0
                ],
                [
                    -4.98,
                    -4.08,
                    0
                ],
                [
                    -3.23,
                    -3.81,
                    0
                ],
                [
                    -2.96,
                    -5.56,
                    0
                ]
            ]
        },
        {
            "id": 8,
            "name": "nf_8",
            "cartesian_points": [
                [
                    -2.81,
                    -1.16,
                    0
                ],
                [
                    -4.2,
                    -0.44,
                    0
                ],
                [
                    -3.48,
                    0.94,
                    0
                ],
                [
                    -2.09,
                    0.22,
                    0
                ]
            ]
        },
        {
            "id": 9,
            "name": "nf_9",
            "cartesian_points": [
                [
                    -1.89,
                    -7.62,
                    0
                ],
                [
                    -3.17,
                    -8.02,
                    0
                ],
                [
                    -3.57,
                    -6.74,
                    0
                ],
                [
                    -2.29,
                    -6.34,
                    0
                ]
            ]
        },
        {
            "id": 10,
            "name": "nf_10",
            "cartesian_points": [
                [
                    0.61,
                    -5.32,
                    0
                ],
                [
                    0.59,
                    -4.86,
                    0
                ],
                [
                    1.05,
                    -4.84,
                    0
                ],
                [
                    1.07,
                    -5.3,
                    0
                ]
            ]
        },
        {
            "id": 11,
            "name": "nf_11",
            "cartesian_points": [
                [
                    -1.06,
                    -5.19,
                    0
                ],
                [
                    -1.78,
                    -5.9,
                    0
                ],
                [
                    -2.49,
                    -5.18,
                    0
                ],
                [
                    -1.77,
                    -4.47,
                    0
                ]
            ]
        },
        {
            "id": 12,
            "name": "nf_12",
            "cartesian_points": [
                [
                    -0.58,
                    -4.13,
                    0
                ],
                [
                    -1.46,
                    -3.98,
                    0
                ],
                [
                    -1.31,
                    -3.09,
                    0
                ],
                [
                    -0.42,
                    -3.25,
                    0
                ]
            ]
        },
        {
            "id": 13,
            "name": "nf_13",
            "cartesian_points": [
                [
                    2.85,
                    -7.64,
                    0
                ],
                [
                    1.5,
                    -7.61,
                    0
                ],
                [
                    1.53,
                    -6.27,
                    0
                ],
                [
                    2.87,
                    -6.29,
                    0
                ]
            ]
        },
        {
            "id": 14,
            "name": "nf_14",
            "cartesian_points": [
                [
                    -2.57,
                    -10.09,
                    0
                ],
                [
                    -3.93,
                    -11.1,
                    0
                ],
                [
                    -4.94,
                    -9.75,
                    0
                ],
                [
                    -3.59,
                    -8.73,
                    0
                ]
            ]
        },
        {
            "id": 15,
            "name": "nf_15",
            "cartesian_points": [
                [
                    -1.92,
                    -4.67,
                    0
                ],
                [
                    -2.28,
                    -4.96,
                    0
                ],
                [
                    -2.58,
                    -4.6,
                    0
                ],
                [
                    -2.21,
                    -4.3,
                    0
                ]
            ]
        },
        {
            "id": 16,
            "name": "nf_16",
            "cartesian_points": [
                [
                    -3.16,
                    -4.6,
                    0
                ],
                [
                    -3.18,
                    -3.28,
                    0
                ],
                [
                    -1.86,
                    -3.26,
                    0
                ],
                [
                    -1.84,
                    -4.57,
                    0
                ]
            ]
        },
        {
            "id": 17,
            "name": "nf_17",
            "cartesian_points": [
                [
                    3.66,
                    -6.47,
                    0
                ],
                [
                    2.92,
                    -7.42,
                    0
                ],
                [
                    1.98,
                    -6.69,
                    0
                ],
                [
                    2.71,
                    -5.74,
                    0
                ]
            ]
        },
        {
            "id": 18,
            "name": "nf_18",
            "cartesian_points": [
                [
                    -2.43,
                    -5.58,
                    0
                ],
                [
                    -3.26,
                    -4.25,
                    0
                ],
                [
                    -1.92,
                    -3.42,
                    0
                ],
                [
                    -1.1,
                    -4.76,
                    0
                ]
            ]
        },
        {
            "id": 19,
            "name": "nf_19",
            "cartesian_points": [
                [
                    -1.37,
                    -6.45,
                    0
                ],
                [
                    -2.39,
                    -5.63,
                    0
                ],
                [
                    -1.56,
                    -4.61,
                    0
                ],
                [
                    -0.55,
                    -5.44,
                    0
                ]
            ]
        }
    ]
}